tiskit/__init__.py
tiskit/clean_rotator.py
tiskit/read_mseed.py
tiskit/time_spans.py
tiskit/transfer_functions.py
tiskit/version.py
tiskit/data_cleaner/__init__.py
tiskit/data_cleaner/cleaner_string.py
tiskit/data_cleaner/data_cleaner_tf.py
tiskit/data_cleaner/dctfs.py
tiskit/decimate/.DS_Store
tiskit/decimate/ToDo.md
tiskit/decimate/__init__.py
tiskit/decimate/decimate_SDS.py
tiskit/decimate/decimator.py
tiskit/decimate/fir_filter.py
tiskit/decimate/version.py
tiskit/decimate/__pycache__/FIR_filter.cpython-38.pyc
tiskit/decimate/__pycache__/PSD.cpython-38.pyc
tiskit/decimate/__pycache__/Peterson_noise_model.cpython-38.pyc
tiskit/decimate/__pycache__/__init__.cpython-38.pyc
tiskit/decimate/__pycache__/coherence.cpython-38.pyc
tiskit/decimate/__pycache__/decimate.cpython-38.pyc
tiskit/decimate/__pycache__/decimate_SDS.cpython-38.pyc
tiskit/decimate/__pycache__/decimator.cpython-38.pyc
tiskit/decimate/__pycache__/transfer_function.cpython-38.pyc
tiskit/decimate/__pycache__/utils.cpython-38.pyc
tiskit/decimate/sac_fir/dec2
tiskit/decimate/sac_fir/dec3
tiskit/decimate/sac_fir/dec4
tiskit/decimate/sac_fir/dec5
tiskit/decimate/sac_fir/dec6
tiskit/decimate/sac_fir/dec7
tiskit/fir_corr/__init__.py
tiskit/fir_corr/fir2caus.py
tiskit/rptransient/__init__.py
tiskit/rptransient/dirac_comb.py
tiskit/rptransient/periodic_transient.py
tiskit/rptransient/transients.py
tiskit/rptransient/utils.py
tiskit/rptransient/version.py
tiskit/spectral_density/Peterson_noise_model.py
tiskit/spectral_density/__init__.py
tiskit/spectral_density/spectral_density.py
tiskit/spectral_density/utils.py
tiskit/spectral_density/version.py
tiskit/utils/__init__.py
tiskit/utils/seis_rotate.py
tiskit_py-0.3.2.dist-info/LICENSE.txt
tiskit_py-0.3.2.dist-info/METADATA
tiskit_py-0.3.2.dist-info/WHEEL
tiskit_py-0.3.2.dist-info/entry_points.txt
tiskit_py-0.3.2.dist-info/top_level.txt
tiskit_py-0.3.2.dist-info/RECORD
