Metadata-Version: 2.1
Name: tiskit-py
Version: 0.3.2
Summary: TIme Series  toolKIT
Home-page: https://github.com/WayneCrawford/tiskit
Author: Wayne Crawford
Author-email: crawford@ipgp.fr
Keywords: oceanography,marine,OBS
Classifier: Development Status :: 4 - Beta
Classifier: Environment :: Console
Classifier: Intended Audience :: Science/Research
Classifier: Intended Audience :: Developers
Classifier: License :: OSI Approved :: GNU General Public License v3 (GPLv3)
Classifier: Natural Language :: English
Classifier: Operating System :: OS Independent
Classifier: Programming Language :: Python :: 3.6
Classifier: Topic :: Scientific/Engineering
Classifier: Topic :: Scientific/Engineering :: Physics
Requires-Python: >=3.8
License-File: LICENSE.txt
Requires-Dist: obspy (>=1.3.0)
Requires-Dist: PyYAML
Requires-Dist: numpy
Requires-Dist: scipy
Requires-Dist: matplotlib
Requires-Dist: xarray
